op_orm/__init__.py
op_orm/client.py
op_orm/deployment_generator.py
op_orm/exceptions.py
op_orm/fields.py
op_orm/models.py
op_orm/types.py
op_orm-0.1.0.dist-info/LICENSE.txt
op_orm-0.1.0.dist-info/METADATA
op_orm-0.1.0.dist-info/WHEEL
op_orm-0.1.0.dist-info/entry_points.txt
op_orm-0.1.0.dist-info/top_level.txt
op_orm-0.1.0.dist-info/RECORD
