Metadata-Version: 2.2
Name: op-orm
Version: 0.1.0
Summary: Object Relational Mapping for 1Password items, manage 1Password vaults with code.
Author-email: Ilke <github@ilke.dev>
Maintainer-email: Ilke <github@ilke.dev>
License:    GNU GENERAL PUBLIC LICENSE
Keywords: 1password,orm,op,op-orm,onepassword,onepassword-sdk,devops,secret-management,password-manager,credentials,security,kubernetes,k8s,vault,secret-management,secret-store,api-keys,database-credentials,ssh-keys,infrastructure,automation,configuration-management
Classifier: Intended Audience :: Developers
Classifier: Intended Audience :: System Administrators
Classifier: Topic :: Security
Classifier: Topic :: Security :: Cryptography
Classifier: Topic :: Software Development :: Libraries :: Python Modules
Classifier: Topic :: System :: Systems Administration
Classifier: Programming Language :: Python :: 3
Classifier: Operating System :: OS Independent
Requires-Python: >=3.12
License-File: LICENSE.txt
Requires-Dist: onepassword-sdk
Requires-Dist: jinja2
Provides-Extra: dev
Requires-Dist: pytest; extra == "dev"
Requires-Dist: debugpy; extra == "dev"
Requires-Dist: twine; extra == "dev"
Requires-Dist: build; extra == "dev"
